MANIFEST.in
README.txt
requirements.txt
setup.py
pybamview/__init__.py
pybamview/__main__.py
pybamview/app.py
pybamview/bam_alignment.py
pybamview/cli.py
pybamview/constants.py
pybamview/settings.py
pybamview/snapshot.js
pybamview/snapshot.py
pybamview/utils.py
pybamview.egg-info/PKG-INFO
pybamview.egg-info/SOURCES.txt
pybamview.egg-info/dependency_links.txt
pybamview.egg-info/entry_points.txt
pybamview.egg-info/requires.txt
pybamview.egg-info/top_level.txt
pybamview/browser/__init__.py
pybamview/browser/views.py
pybamview/browser/static/css/pybamview.css
pybamview/browser/static/img/favicon.ico
pybamview/browser/static/img/question_mark.png
pybamview/browser/static/javascript/alignments.js
pybamview/browser/static/javascript/pybamview.js
pybamview/browser/templates/bamview.html
pybamview/browser/templates/error.html
pybamview/browser/templates/index.html
pybamview/browser/templates/snapshot.html
pybamview/tests/__init__.py
pybamview/tests/test_bam_view.py
pybamview/tests/data/test_1.bam
pybamview/tests/data/test_1.bam.bai
pybamview/tests/data/test_2.bam
pybamview/tests/data/test_2.bam.bai