Metadata-Version: 1.1
Name: pybamview
Version: 1.0.8
Summary: Python based BAM alignment viewer
Home-page: http://github.com/mgymrek/pybamview
Author: Melissa Gymrek
Author-email: mgymrek@mit.edu
License: MIT
Download-URL: http://github.com/mgymrek/pybamview
Platform: UNKNOWN
Classifier: Development Status :: 4 - Beta
Classifier: Programming Language :: Python :: 2.6
Classifier: License :: OSI Approved :: MIT License
Classifier: Operating System :: OS Independent
Classifier: Intended Audience :: Science/Research
Classifier: Topic :: Scientific/Engineering :: Bio-Informatics
Classifier: Topic :: Scientific/Engineering :: Visualization
